MANIFEST.in
README.md
VERSION.txt
setup.cfg
setup.py
pyserialize/__init__.py
pyserialize.egg-info/PKG-INFO
pyserialize.egg-info/SOURCES.txt
pyserialize.egg-info/dependency_links.txt
pyserialize.egg-info/top_level.txt