Metadata-Version: 1.1
Name: pyserialize
Version: 1.0.2
Summary: Python simple serializer
Home-page: https://github.com/juhgiyo/pyserialize
Author: Woong Gyu La
Author-email: juhgiyo@gmail.com
License: The MIT License (MIT)
Keywords: serialize,pack,unpack,library
Platform: UNKNOWN
Classifier: Development Status :: 5 - Production/Stable
Classifier: Programming Language :: Python :: 2.7
Classifier: Programming Language :: Python :: 3
